trollmaker/__init__.py
trollmaker/main.py
trollmaker/prompts.py
trollmaker-2025.12.21115254.dist-info/METADATA
trollmaker-2025.12.21115254.dist-info/WHEEL
trollmaker-2025.12.21115254.dist-info/top_level.txt
trollmaker-2025.12.21115254.dist-info/RECORD
