Metadata-Version: 2.4
Name: trollmaker
Version: 2025.12.21115254
Summary: A new package that allows users to input a public username or handle from social media platforms, and receives a structured, humorous roast based on publicly available information. The package uses ll
Author-email: trollmaker <hi@eugene.plus>
License: MIT
Project-URL: Homepage, https://github.com/chigwell/trollmaker
Requires-Python: >=3.9
Requires-Dist: langchain-llm7>=0.0.0
Requires-Dist: llmatch-messages>=0.0.0
Requires-Dist: langchain-core>=0.3.0
